stitchnet/__init__.py
stitchnet/ensemble/__init__.py
stitchnet/ensemble/ensemble.py
stitchnet/finetuning/__init__.py
stitchnet/finetuning/finetune.py
stitchnet/finetuning/finetune2.py
stitchnet/plot/__init__.py
stitchnet/plot/plotutils.py
stitchnet/stitchonnx/CKA.py
stitchnet/stitchonnx/__init__.py
stitchnet/stitchonnx/ptCKA.py
stitchnet/stitchonnx/render.py
stitchnet/stitchonnx/report.py
stitchnet/stitchonnx/utils.py
stitchnet/stitchonnx/viz.py
stitchnet-0.2.2.dist-info/WHEEL
stitchnet-0.2.2.dist-info/METADATA
stitchnet-0.2.2.dist-info/RECORD
