Metadata-Version: 2.1
Name: stitchnet
Version: 0.2.2
Summary: 
Author: Surat Teerapittayanon
Author-email: steerapi@gmail.com
Requires-Python: >=3.9,<3.12
Classifier: Programming Language :: Python :: 3
Classifier: Programming Language :: Python :: 3.10
Classifier: Programming Language :: Python :: 3.9
Requires-Dist: datasets (>=2.13.1,<3.0.0)
Requires-Dist: evaluate (>=0.4.0,<0.5.0)
Requires-Dist: graphviz (>=0.20.1,<0.21.0)
Requires-Dist: netron (>=7.0.4,<8.0.0)
Requires-Dist: numpy (>=1.23.1,<2.0.0)
Requires-Dist: onnx (==1.13.1)
Requires-Dist: onnx-tool (==0.7.3)
Requires-Dist: onnx2torch (>=1.4.1,<2.0.0)
Requires-Dist: onnxoptimizer (>=0.3.0,<0.4.0)
Requires-Dist: onnxruntime (>=1.12.1,<2.0.0)
Requires-Dist: pyppeteer (>=1.0.2,<2.0.0)
Requires-Dist: pyre-extensions (>=0.0.30,<0.0.31)
Requires-Dist: scipy (>=1.7.3,<2.0.0)
Requires-Dist: seaborn (>=0.11.2,<0.12.0)
Requires-Dist: skl2onnx (>=1.12.0,<1.13.0)
Requires-Dist: torch (>=1.12.1,<2.0.0)
Requires-Dist: torchvision (>=0.13.1,<0.14.0)
Requires-Dist: transformers (>=4.25.1,<5.0.0)
